{
  "rediriger_vers_presentation_personnelle": {
    "description": "Rediriger vers la page de présentation personnelle",
    "href": "/a-propos"
  },
  "rediriger_vers_manifeste_ia": {
    "description": "Rediriger vers le manifeste de l'IA",
    "href": "/ai"
  },
  "rediriger_vers_dernier_article": {
    "description": "Rediriger vers le dernier article de blog",
    "href": "/blog/dernier-article"
  },
  "rediriger_vers_tous_les_articles": {
    "description": "Rediriger vers tous les articles de blog",
    "href": "/blog"
  },
  "rediriger_vers_contact": {
    "description": "Rediriger vers la page de contact",
    "href": "/contact"
  },
  "rediriger_vers_presentations": {
    "description": "Rediriger vers les présentations",
    "href": "/presentations"
  },
  "rediriger_vers_projets": {
    "description": "Rediriger vers les projets",
    "href": "/projets"
  },
  "rediriger_vers_page_chat": {
    "description": "Rediriger vers la page de présentation du chat",
    "href": "/chat"
  },
  "rediriger_personne_balade": {
    "description": "Rediriger une personne qui se balade sur le site",
    "href": "/blog"
  }
}
